pygpeople/__init__.py
pygpeople/client_secret.json
pygpeople/configs.py
pygpeople/constants.py
pygpeople/main.py
pygpeople/static.py
pygpeople-0.0.3.dist-info/licenses/LICENSE
pygpeople-0.0.3.dist-info/METADATA
pygpeople-0.0.3.dist-info/WHEEL
pygpeople-0.0.3.dist-info/entry_points.txt
pygpeople-0.0.3.dist-info/top_level.txt
pygpeople-0.0.3.dist-info/RECORD
