Metadata-Version: 2.4
Name: pygpeople
Version: 0.0.3
Summary: Manage your contacts in google
Home-page: https://veltzer.github.io/pygpeople
Download-URL: https://github.com/veltzer/pygpeople
Author: Mark Veltzer
Author-email: mark.veltzer@gmail.com
Maintainer: Mark Veltzer
Maintainer-email: mark.veltzer@gmail.com
License: MIT
Keywords: google,contacts,people,python
Platform: python3
Classifier: Development Status :: 4 - Beta
Classifier: Environment :: Console
Classifier: Operating System :: OS Independent
Classifier: Programming Language :: Python
Classifier: Programming Language :: Python :: 3
Classifier: Programming Language :: Python :: 3 :: Only
Classifier: Programming Language :: Python :: 3.12
Classifier: Topic :: Utilities
License-File: LICENSE
Requires-Dist: pygooglehelper
Requires-Dist: google-api-python-client
Requires-Dist: pytconf
Requires-Dist: pylogconf
Dynamic: author
Dynamic: author-email
Dynamic: classifier
Dynamic: description
Dynamic: description-content-type
Dynamic: download-url
Dynamic: home-page
Dynamic: keywords
Dynamic: license
Dynamic: license-file
Dynamic: maintainer
Dynamic: maintainer-email
Dynamic: platform
Dynamic: requires-dist
Dynamic: summary
